Spleen-0.0.1.dist-info/DESCRIPTION.rst
Spleen-0.0.1.dist-info/METADATA
Spleen-0.0.1.dist-info/RECORD
Spleen-0.0.1.dist-info/WHEEL
Spleen-0.0.1.dist-info/metadata.json
Spleen-0.0.1.dist-info/top_level.txt
spleen/__init__.py
spleen/_version.py
