Metadata-Version: 2.0
Name: Spleen
Version: 0.0.1
Summary: idk fix later
Home-page: https://github.com/Brightmd/Spleen
Author: Bright.md
Author-email: cory@bright.md
License: UNKNOWN
Platform: UNKNOWN
Requires-Dist: attrs
